{
  "required": true,
  "minVersion": "0.8",
  "package": "io.github.fukkitmc.legacy.mixins",
  "compatibilityLevel": "JAVA_8",
  "mixins": [
    "craftbukkit.ChunkMixin",
    "craftbukkit.ContainerPlayerMixin",
    "craftbukkit.DedicatedServerMixin",
    "craftbukkit.EntityLivingMixin",
    "craftbukkit.EntityMixin",
    "craftbukkit.HandshakeListenerMixin",
    "craftbukkit.MinecraftServerMixin",
    "craftbukkit.PacketStatusListenerMixin",
    "craftbukkit.PlayerInteractManagerMixin",
    "craftbukkit.PlayerListMixin",
    "extra.ArmorStandMixin",
    "extra.ChunkMixin",
    "extra.ChunkProviderServerMixin",
    "extra.ChunkRegionLoaderMixin",
    "extra.ChunkSectionMixin",
    "extra.ContainerMixin",
    "extra.CraftingManagerMixin",
    "extra.EntityArmorStandMixin",
    "extra.EntityArrowMixin",
    "extra.EntityCreeperMixin",
    "extra.EntityDamageSourceIndirectMixin",
    "extra.EntityFireballMixin",
    "extra.EntityHorseMixin",
    "extra.EntityHumanMixin",
    "extra.EntityLivingMixin",
    "extra.EntityMinecartAbstractMixin",
    "extra.EntityMixin",
    "extra.EntityPlayerMixin",
    "extra.EntityRabbitMixin",
    "extra.IDataManagerMixin",
    "extra.IInventoryMixin",
    "extra.IRecipeMixin",
    "extra.JsonListMixin",
    "extra.MinecraftServerMixin",
    "extra.PlayerChunkMapMixin",
    "extra.PlayerConnectionMixin",
    "extra.PlayerInventoryMixin",
    "extra.PlayerListMixin",
    "extra.PortalTravelAgentMixin",
    "extra.RecipesFurnaceMixin",
    "extra.ScoreboardTeamMixin",
    "extra.WorldChunkManagerMixin",
    "extra.WorldDataMixin",
    "extra.WorldMixin",
    "extra.WorldNBTStorageMixin",
    "extra.WorldServerMixin",
    "fukkit.DedicatedPlayerListMixin"
  ],
  "client": [
  ],
  "injectors": {
    "defaultRequire": 1
  }
}
